oswizard/__init__.py
oswizard/__main__.py
oswizard/cleanup.py
oswizard/cli.py
oswizard/combiner.py
oswizard/config.py
oswizard/errors.py
oswizard/jobs_watch.py
oswizard/machines_cli.py
oswizard/media.py
oswizard/networks_cli.py
oswizard/orchestrator.py
oswizard/partition_spec.py
oswizard/patchqueue.py
oswizard/renderer.py
oswizard/rescue.py
oswizard/state.py
oswizard/types.py
oswizard/vendor_detect.py
oswizard/ventoy_exec.py
oswizard/virtualmedia_probe.py
oswizard/worker.py
oswizard/workspace.py
oswizard/drivers/__init__.py
oswizard/drivers/asrock.py
oswizard/drivers/asrock_rack.py
oswizard/drivers/asrock_rm.py
oswizard/drivers/base.py
oswizard/drivers/dell_idrac.py
oswizard/drivers/hp_ilo.py
oswizard/drivers/hpe_ilo.py
oswizard/drivers/ipmi.py
oswizard/drivers/lenovo_xcc.py
oswizard/drivers/redfish.py
oswizard/drivers/redfish_stub.py
oswizard/render/__init__.py
oswizard/render/autoinstall.py
oswizard/render/cloudinit.py
oswizard/render/ks.py
oswizard/utils/__init__.py
oswizard/utils/bootargs.py
oswizard/utils/csrf.py
oswizard/utils/fetch.py
oswizard/utils/httpd.py
oswizard/utils/httpfetch.py
oswizard/utils/httpserve.py
oswizard/utils/iso.py
oswizard/utils/jobstore.py
oswizard/utils/logger.py
oswizard/utils/logstore.py
oswizard/utils/machinestore.py
oswizard/utils/net.py
oswizard/utils/netdetect.py
oswizard/utils/netparse.py
oswizard/utils/partitions.py
oswizard/utils/reach.py
oswizard/utils/retry.py
oswizard/utils/secrets.py
oswizard/utils/seed.py
oswizard/utils/shell.py
oswizard-0.1.21.dist-info/METADATA
oswizard-0.1.21.dist-info/WHEEL
oswizard-0.1.21.dist-info/entry_points.txt
oswizard-0.1.21.dist-info/top_level.txt
oswizard-0.1.21.dist-info/RECORD
