Metadata-Version: 2.4
Name: oswizard
Version: 0.1.21
Summary: Automated OS provisioning and installation orchestrator
Author-email: OSWizard Dev Team <dev@oswiz.io>
Requires-Python: >=3.9
Requires-Dist: typer>=0.12.3
Requires-Dist: jinja2>=3.1.4
Requires-Dist: rich>=13.7.1
Requires-Dist: pydantic>=2.8.2
Requires-Dist: pyyaml>=6.0.2
Requires-Dist: tenacity>=9.0.0
